vgg_pytorch/__init__.py
vgg_pytorch/model.py
vgg_pytorch/utils.py
vgg_pytorch-0.3.0.dist-info/LICENSE
vgg_pytorch-0.3.0.dist-info/METADATA
vgg_pytorch-0.3.0.dist-info/WHEEL
vgg_pytorch-0.3.0.dist-info/top_level.txt
vgg_pytorch-0.3.0.dist-info/RECORD
