Metadata-Version: 2.1
Name: vgg-pytorch
Version: 0.3.0
Summary: An VGGNet implements of PyTorch.
Home-page: https://github.com/Lornatang/VGGNet-PyTorch
Author: Liu Changyu
Author-email: liuchangyu1111@gmail.com
License: Apache
Platform: UNKNOWN
Classifier: License :: OSI Approved :: Apache Software License
Classifier: Programming Language :: Python
Classifier: Programming Language :: Python :: 3
Classifier: Programming Language :: Python :: 3.6
Classifier: Programming Language :: Python :: 3.7
Requires-Python: >=3.6.0
Requires-Dist: torch
